iharp_query_executor/__init__.py
iharp_query_executor/get_find_area_api.py
iharp_query_executor/get_find_time_api.py
iharp_query_executor/get_geojson_executor.py
iharp_query_executor/get_heatmap_api.py
iharp_query_executor/get_raster_api.py
iharp_query_executor/get_timeseries_api.py
iharp_query_executor-0.1.1.dist-info/METADATA
iharp_query_executor-0.1.1.dist-info/WHEEL
iharp_query_executor-0.1.1.dist-info/top_level.txt
iharp_query_executor-0.1.1.dist-info/RECORD
